{"GUID":"AkKsEQACHt+fl92lptBIwg==","MATNR":"HZ-HYP","MAKTX":"Hydrogen Peroxide 3%","WERKS":"0001","LGORT":"0002","LGOBE":"Cold Storage","SECTION_ID":13,"SECTION_HEADER":"Disposal considerations","SECTION_CONTENT":"Chemical waste generators must determine whether a discarded chemical is classified as a\nhazardous waste. Chemical waste generators must also consult local, regional, and\nnational hazardous waste regulations to ensure complete and accurate classification.","REVISED_CONTENT":"Product ID:HZ-HYP,Product Description:Hydrogen Peroxide 3%,Storage Location:0002,Storage Location Description:Cold Storage,Plant:0001,Section Id:13,Section Header:Disposal considerations,Section Content:Chemical waste generators must determine whether a discarded chemical is classified as a\nhazardous waste. Chemical waste generators must also consult local, regional, and\nnational hazardous waste regulations to ensure complete and accurate classification."}