{"GUID":"AkKsEQACHt+fl92lo2Dowg==","MATNR":"HZ-GAS","MAKTX":"Gasoline","WERKS":"0001","LGORT":"0001","LGOBE":"Lager 0001","SECTION_ID":14,"SECTION_HEADER":"Transport information","SECTION_CONTENT":"SEA (IMDG)\nProper Shipping Name: MOTOR SPIRIT or GASOLINE or PETROL\nHazard Class & Division: 3\nF-E, S-E\nEMS Number:\nUN Number:\n1203\nPacking Group:\n||\nMarine Pollutant: Yes\nLabel(s): 3\nTransport Document Name: MARINE POLLUTANT\nUN1203, MOTOR SPIRIT or GASOLINE or PETROL, 3, PG II, (-35°C с.с.),\nNote - this material is being carried under the scope of MARPOL Annex I","REVISED_CONTENT":"Product ID:HZ-GAS,Product Description:Gasoline,Storage Location:0001,Storage Location Description:Lager 0001,Plant:0001,Section Id:14,Section Header:Transport information,Section Content:SEA (IMDG)\nProper Shipping Name: MOTOR SPIRIT or GASOLINE or PETROL\nHazard Class & Division: 3\nF-E, S-E\nEMS Number:\nUN Number:\n1203\nPacking Group:\n||\nMarine Pollutant: Yes\nLabel(s): 3\nTransport Document Name: MARINE POLLUTANT\nUN1203, MOTOR SPIRIT or GASOLINE or PETROL, 3, PG II, (-35°C с.с.),\nNote - this material is being carried under the scope of MARPOL Annex I"}